lya/__init__.py
lya/lya.py
layered_yaml_attrdict_config-18.12.3.dist-info/COPYING
layered_yaml_attrdict_config-18.12.3.dist-info/METADATA
layered_yaml_attrdict_config-18.12.3.dist-info/WHEEL
layered_yaml_attrdict_config-18.12.3.dist-info/top_level.txt
layered_yaml_attrdict_config-18.12.3.dist-info/RECORD
