Metadata-Version: 2.1
Name: layered-yaml-attrdict-config
Version: 18.12.3
Summary: YAML-based configuration module
Home-page: https://github.com/mk-fg/layered-yaml-attrdict-config
Author: Mike Kazantsev
Author-email: mk.fraggod@gmail.com
License: WTFPL
Keywords: yaml configuration conf serialization inheritance merge update
Platform: UNKNOWN
Classifier: Development Status :: 4 - Beta
Classifier: Intended Audience :: Developers
Classifier: License :: OSI Approved
Classifier: Operating System :: POSIX
Classifier: Operating System :: Unix
Classifier: Programming Language :: Python
Classifier: Programming Language :: Python :: 2
Classifier: Programming Language :: Python :: 2.7
Classifier: Programming Language :: Python :: 3
Classifier: Programming Language :: Python :: 3.2
Classifier: Programming Language :: Python :: 3.3
Classifier: Programming Language :: Python :: 3.4
Classifier: Topic :: Software Development
Classifier: Topic :: Software Development :: Libraries :: Python Modules
Requires-Dist: PyYAML
